SacraPhysicsEngine/Gravity.py
SacraPhysicsEngine/Movement.py
SacraPhysicsEngine/State.py
SacraPhysicsEngine/__init__.py
SacraPhysicsEngine-0.0.1.dist-info/LICENSE
SacraPhysicsEngine-0.0.1.dist-info/METADATA
SacraPhysicsEngine-0.0.1.dist-info/WHEEL
SacraPhysicsEngine-0.0.1.dist-info/top_level.txt
SacraPhysicsEngine-0.0.1.dist-info/RECORD
