Metadata-Version: 2.1
Name: SacraPhysicsEngine
Version: 0.0.1
Summary: A lightweight physics-engine package with intents of being used in Sacra Game Engine
Home-page: UNKNOWN
Author: Andreas Evensen
Author-email: Andreas.evensen11@gmail.com
License: MIT
Platform: UNKNOWN
Classifier: Development Status :: 3 - Alpha
Classifier: Intended Audience :: Developers
Classifier: License :: OSI Approved :: MIT License
